stacki3/__init__.py
stacki3/__main__.py
stacki3-1.0.0.dist-info/entry_points.txt
stacki3-1.0.0.dist-info/LICENSE
stacki3-1.0.0.dist-info/WHEEL
stacki3-1.0.0.dist-info/METADATA
stacki3-1.0.0.dist-info/RECORD
