Metadata-Version: 2.1
Name: stacki3
Version: 1.0.0
Summary: Stack layout for i3/sway wm.
Home-page: https://github.com/ViliamV/stacki3
License: MIT
Author: Viliam Valent
Author-email: stacki3@viliamvalent.com
Requires-Python: >=3.8,<4.0
Classifier: License :: OSI Approved :: MIT License
Classifier: Programming Language :: Python :: 3
Classifier: Programming Language :: Python :: 3.8
Classifier: Programming Language :: Python :: 3.9
Requires-Dist: i3ipc (>=2.2.1,<3.0.0)
Project-URL: Repository, https://github.com/ViliamV/stacki3
